malmoenv/__init__.py
malmoenv/bootstrap.py
malmoenv/commands.py
malmoenv/comms.py
malmoenv/core.py
malmoenv/version.py
malmoenv-0.0.8.dist-info/DESCRIPTION.rst
malmoenv-0.0.8.dist-info/METADATA
malmoenv-0.0.8.dist-info/RECORD
malmoenv-0.0.8.dist-info/WHEEL
malmoenv-0.0.8.dist-info/metadata.json
malmoenv-0.0.8.dist-info/top_level.txt
proxyenv/__init__.py
proxyenv/action_utils.py
proxyenv/client.py
proxyenv/comms.py
proxyenv/malmo_proxyenv_client.py
proxyenv/malmo_proxyenv_serv.py
proxyenv/malmoenvwrap.py
proxyenv/minerl_proxyenv_client.py
proxyenv/minerl_proxyenv_serv.py
proxyenv/server.py
