Metadata-Version: 1.1
Name: malmoenv
Version: 0.0.8
Summary: A gym environemnt for Malmo
Home-page: https://github.com/Microsoft/malmo
Author: Andre Kramer
Author-email: v-andkra@microsoft.com
License: UNKNOWN
Platform: UNKNOWN
Classifier: Programming Language :: Python :: 3
Classifier: License :: OSI Approved :: MIT License
Classifier: Operating System :: OS Independent
